Metadata-Version: 2.4
Name: x17-lib-base
Version: 0.1.0
Summary: Core utility library for data types, time, and platform utilities
Author-email: Xing Xing <x.xing.work@gmail.com>
License: MIT
Requires-Python: >=3.10
Requires-Dist: pytz>=2024.1
Requires-Dist: python-dateutil>=2.8
Requires-Dist: pyawscron>=1.0.7
Requires-Dist: holidays>=0.70
Requires-Dist: boto3>=1.37.31
Requires-Dist: moto[boto3]>=5.1.3
Requires-Dist: jmespath>=1.0.1
Requires-Dist: psutil>=7.0.0
